python_spore_codec-0.3.1.dist-info/DESCRIPTION.rst
python_spore_codec-0.3.1.dist-info/METADATA
python_spore_codec-0.3.1.dist-info/RECORD
python_spore_codec-0.3.1.dist-info/WHEEL
python_spore_codec-0.3.1.dist-info/metadata.json
python_spore_codec-0.3.1.dist-info/top_level.txt
spore_codec/__init__.py
spore_codec/core.py
spore_codec/decode.py
spore_codec/document.py
spore_codec/encode.py
spore_codec/helpers.py
