Metadata-Version: 2.0
Name: python-spore-codec
Version: 0.3.1
Summary: Spore codec for CoreAPI specification
Home-page: https://github.com/unistra/python-spore-codec
Author: Arnaud Grausem
Author-email: arnaud.grausem@gmail.com
License: GPLv3
Keywords: coreapi spore api-description rest-api
Platform: UNKNOWN
Classifier: Development Status :: 3 - Alpha
Classifier: Intended Audience :: Developers
Classifier: Topic :: Software Development :: Libraries
Classifier: Environment :: Web Environment
Classifier: License :: OSI Approved :: GNU General Public License v3 (GPLv3)
Classifier: Operating System :: OS Independent
Classifier: Programming Language :: Python :: 3.4
Classifier: Programming Language :: Python :: 3.5
Classifier: Programming Language :: Python :: 3.6
Requires-Dist: coreapi
